ctrlai_core/__init__.py
ctrlai_core/constants.py
ctrlai_core/docs/__init__.py
ctrlai_core/docs/schema.json
ctrlai_core/logging_config.py
ctrlai_core/models.py
ctrlai_core/utils.py
ctrlai_core/validate.py
ctrlai_core-1.0.4.dist-info/LICENSE
ctrlai_core-1.0.4.dist-info/METADATA
ctrlai_core-1.0.4.dist-info/WHEEL
ctrlai_core-1.0.4.dist-info/RECORD
