Metadata-Version: 2.3
Name: ctrlai-core
Version: 1.0.4
Summary: Core functionality for Ctrl AI - A standardized protocol for managing AI interactions and personalized AI knowledge
License: MIT
Keywords: ai,control,validation,json-ld,schema,ai-control,ai-protocol,personalization
Author: Ctrl AI Team
Author-email: info@ctrlai.com
Requires-Python: >=3.9
Classifier: Development Status :: 4 - Beta
Classifier: Intended Audience :: Developers
Classifier: License :: OSI Approved :: MIT License
Classifier: Programming Language :: Python :: 3
Classifier: Programming Language :: Python :: 3.9
Classifier: Programming Language :: Python :: 3.10
Classifier: Programming Language :: Python :: 3.11
Classifier: Topic :: Software Development :: Libraries :: Python Modules
Classifier: Topic :: Scientific/Engineering :: Artificial Intelligence
Requires-Dist: flake8 (==6.1.0)
Requires-Dist: jsonschema (>=4.0.0)
Requires-Dist: pydantic (>=2.0.0)
Project-URL: Bug Tracker, https://github.com/ctrl-ai/ctrlai-core/issues
Project-URL: Documentation, https://ctrlai-core.readthedocs.io/
Project-URL: Homepage, https://github.com/ctrl-ai/ctrlai-core
Project-URL: Repository, https://github.com/ctrl-ai/ctrlai-core
